{
  "__inputs": [],
  "__elements": {},
  "__requires": [
    {
      "type": "grafana",
      "id": "grafana",
      "name": "Grafana",
      "version": "9.1.8"
    },
    {
      "type": "datasource",
      "id": "ibm-rmf-datasource",
      "name": "IBM RMF for z/OS",
      "version": "%VERSION%"
    },
    {
      "type": "panel",
      "id": "ibm-rmf-report",
      "name": "Report for IBM RMF for z/OS",
      "version": "%VERSION%"
    }
  ],
  "annotations": {
    "list": [
      {
        "builtIn": 1,
        "datasource": {
          "type": "datasource",
          "uid": "grafana"
        },
        "enable": true,
        "hide": true,
        "iconColor": "rgba(0, 211, 255, 1)",
        "name": "Annotations & Alerts",
        "target": {
          "limit": 100,
          "matchAny": false,
          "tags": [],
          "type": "dashboard"
        },
        "type": "dashboard"
      }
    ]
  },
  "editable": true,
  "fiscalYearStartMonth": 0,
  "graphTooltip": 0,
  "id": null,
  "liveNow": false,
  "panels": [
    {
      "datasource": {
        "type": "ibm-rmf-datasource",
        "uid": "${datasource}"
      },
      "description": "I/O Channels",
      "fieldConfig": {
        "defaults": {
          "color": {
            "mode": "thresholds"
          },
          "custom": {
            "displayMode": "Auto",
            "enablePagination": false,
            "filterable": false
          },
          "mappings": [],
          "thresholds": {
            "mode": "absolute",
            "steps": [
              {
                "color": "green",
                "value": null
              },
              {
                "color": "red",
                "value": 80
              }
            ]
          }
        },
        "overrides": []
      },
      "gridPos": {
        "h": 22,
        "w": 24,
        "x": 0,
        "y": 0
      },
      "id": 2,
      "targets": [
        {
          "datasource": {
            "type": "ibm-rmf-datasource",
            "uid": "${datasource}"
          },
          "refId": "A",
          "rmfPanelGuid": "9f386c5a-cffd-4367-8065-189a5e4fe925",
          "selectedQuery": "MVS_IMAGE.REPORT.CHANNEL{name=$LPAR}",
          "selectedResource": {
            "label": "report=CHANNEL&resource=,$LPAR,MVS_IMAGE",
            "value": "report=CHANNEL&resource=,$LPAR,MVS_IMAGE"
          },
          "selectedVisualisationType": "table"
        }
      ],
      "title": "CHANNEL",
      "transformations": [
        {
          "id": "organize",
          "options": {
            "excludeByName": {
              "Channel Measurement Group": true,
              "FICON Deferred Operation Rate": true,
              "LPAR MSG Rate": true,
              "LPAR MSG Size": true,
              "LPAR Receive Fail": true,
              "LPAR Send Fail": true,
              "Line Type (DDS)": true,
              "Physical Network ID Port 1": true,
              "Physical Network ID Port 2": true,
              "Total MSG Rate": true,
              "Total MSG Size": true,
              "Total Receive Fail": true,
              "zHPF Deferred Operation Rate": true
            },
            "indexByName": {},
            "renameByName": {}
          }
        }
      ],
      "type": "ibm-rmf-report"
    }
  ],
  "refresh": "1m",
  "schemaVersion": 37,
  "style": "dark",
  "tags": ["RMF", "REPORT"],
  "templating": {
    "list": [
      {
        "current": {
          "selected": false,
          "text": "${datasource}",
          "value": "${datasource}"
        },
        "hide": 0,
        "includeAll": false,
        "label": "Data source",
        "multi": false,
        "name": "datasource",
        "options": [],
        "query": "ibm-rmf-datasource",
        "queryValue": "",
        "refresh": 1,
        "regex": "",
        "skipUrlSync": false,
        "type": "datasource"
      },
      {
        "datasource": {
          "type": "ibm-rmf-datasource",
          "uid": "${datasource}"
        },
        "definition": "sysplex",
        "hide": 0,
        "includeAll": false,
        "multi": false,
        "name": "sysplex",
        "label": "Sysplex",
        "options": [],
        "query": "sysplex",
        "refresh": 1,
        "regex": "",
        "skipUrlSync": false,
        "sort": 0,
        "type": "query",
        "allowCustomValue": false
      },
      {
        "datasource": {
          "type": "ibm-rmf-datasource",
          "uid": "${datasource}"
        },
        "definition": "systems",
        "hide": 0,
        "includeAll": false,
        "multi": false,
        "name": "LPAR",
        "options": [],
        "query": "systems",
        "refresh": 1,
        "regex": "",
        "skipUrlSync": false,
        "sort": 0,
        "type": "query"
      }
    ]
  },
  "time": {
    "from": "now-1m",
    "to": "now"
  },
  "timepicker": {},
  "timezone": "",
  "title": "CHANNEL",
  "version": 1,
  "weekStart": ""
}
